incx/__init__.py
incx/data_models/increx_output.py
incx/dependencies/d_rise/vision_explanation_methods/DRISE_runner.py
incx/dependencies/d_rise/vision_explanation_methods/error_labeling/__init__.py
incx/dependencies/d_rise/vision_explanation_methods/error_labeling/error_labeling.py
incx/dependencies/d_rise/vision_explanation_methods/evaluation/__init__.py
incx/dependencies/d_rise/vision_explanation_methods/evaluation/pointing_game.py
incx/dependencies/d_rise/vision_explanation_methods/explanations/.gitkeep
incx/dependencies/d_rise/vision_explanation_methods/explanations/__init__.py
incx/dependencies/d_rise/vision_explanation_methods/explanations/common.py
incx/dependencies/d_rise/vision_explanation_methods/explanations/drise.py
incx/dependencies/d_rise/vision_explanation_methods/images/.gitkeep
incx/dependencies/d_rise/vision_explanation_methods/models/.gitkeep
incx/dependencies/d_rise/vision_explanation_methods/res/.gitkeep
incx/dependencies/sort/sort.py
incx/explainers/base_explainer.py
incx/explainers/d_rise.py
incx/explainers/explainer_enum.py
incx/explainers/explainer_factory.py
incx/metrics/comparison/explanations/dice_coefficient.py
incx/metrics/comparison/explanations/haussdorf_distance.py
incx/metrics/comparison/explanations/jaccard_index.py
incx/metrics/comparison/saliency_maps/pearson_coefficient.py
incx/metrics/comparison/saliency_maps/structural_similarity_index.py
incx/metrics/saliency_maps/deletion.py
incx/metrics/saliency_maps/epg.py
incx/metrics/saliency_maps/exp_proportion.py
incx/metrics/saliency_maps/insertion.py
incx/metrics/saliency_maps/metrics_enum.py
incx/models/base_model.py
incx/models/faster_rcnn.py
incx/models/labels.py
incx/models/model_enum.py
incx/models/model_factory.py
incx/models/rt_detr.py
incx/models/yolo.py
incx/tracking/exp_tracker.py
incx/tracking/incx.py
incx/transformations/image_moving.py
incx/transformations/image_scaling.py
incx/utils/common.py
incx/utils/explanations.py
incx/utils/save_results.py
incx/utils/video.py
incx-0.0.2.dist-info/METADATA
incx-0.0.2.dist-info/WHEEL
incx-0.0.2.dist-info/RECORD
