Metadata-Version: 2.1
Name: incx
Version: 0.0.2
Summary: 
Author: Santiago Calderón
Author-email: santiagocalderon1999@gmail.com
Requires-Python: >=3.10,<3.13
Classifier: Programming Language :: Python :: 3
Classifier: Programming Language :: Python :: 3.10
Classifier: Programming Language :: Python :: 3.11
Classifier: Programming Language :: Python :: 3.12
Requires-Dist: azure-identity (>=1.17.1,<2.0.0)
Requires-Dist: azure-storage-blob (>=12.21.0,<13.0.0)
Requires-Dist: captum (>=0.7.0,<0.8.0)
Requires-Dist: cvzone (>=1.6.1,<2.0.0)
Requires-Dist: dill (>=0.3.8,<0.4.0)
Requires-Dist: filterpy (>=1.4.5,<2.0.0)
Requires-Dist: ipykernel (>=6.29.5,<7.0.0)
Requires-Dist: matplotlib (==3.6.3)
Requires-Dist: ml-wrappers (>=0.5.5,<0.6.0)
Requires-Dist: numpy (==1.26.0)
Requires-Dist: opencv-python (==4.9.0.80)
Requires-Dist: pydantic (>=2.8.2,<3.0.0)
Requires-Dist: python-dotenv (>=1.0.1,<2.0.0)
Requires-Dist: ruff (>=0.5.6,<0.6.0)
Requires-Dist: scikit-image (>=0.24.0,<0.25.0)
Requires-Dist: seaborn (>=0.13.2,<0.14.0)
Requires-Dist: torch (>=2.3.1,<3.0.0)
Requires-Dist: torchvision (>=0.18.1,<0.19.0)
Requires-Dist: ultralytics (==8.2.55)
